hpt/__init__.py
hpt/_version.py
hpt/binarize.py
hpt/evaluation.py
hpt/suggest.py
hpt/thresholding_evaluation.py
hpt/tuner.py
hpt/utils/__init__.py
hpt/utils/api.py
hpt/utils/classpath.py
hpt/utils/dict.py
hpt/utils/fairness_criteria.py
hpt/utils/load_yaml.py
hpt/utils/trial.py
hyperparameter_tuning-0.3.2.dist-info/LICENSE
hyperparameter_tuning-0.3.2.dist-info/METADATA
hyperparameter_tuning-0.3.2.dist-info/WHEEL
hyperparameter_tuning-0.3.2.dist-info/top_level.txt
hyperparameter_tuning-0.3.2.dist-info/RECORD
