Metadata-Version: 2.1
Name: hyperparameter-tuning
Version: 0.3.2
Summary: A minimal framework for running hyperparameter tuning
Home-page: https://github.com/AndreFCruz/hpt
Author: AndreFCruz
License: MIT
Keywords: ml,optimization,hyperparameter,tuning,fairness
Classifier: Development Status :: 3 - Alpha
Classifier: License :: OSI Approved :: MIT License
Classifier: Intended Audience :: Science/Research
Classifier: Topic :: Scientific/Engineering :: Artificial Intelligence
Classifier: Natural Language :: English
Classifier: Programming Language :: Python :: 3
Classifier: Programming Language :: Python :: 3.8
Classifier: Programming Language :: Python :: 3.9
Classifier: Programming Language :: Python :: 3.10
Classifier: Programming Language :: Python :: 3.11
Classifier: Programming Language :: Python :: 3.12
Requires-Python: >=3.8
License-File: LICENSE
Requires-Dist: optuna
Requires-Dist: numpy
Requires-Dist: pandas
Requires-Dist: scikit-learn >=1.2
Requires-Dist: pyyaml
Requires-Dist: schema
Provides-Extra: all
Requires-Dist: matplotlib ; extra == 'all'
Requires-Dist: seaborn ; extra == 'all'
Requires-Dist: pytest ; extra == 'all'
Provides-Extra: plotting
Requires-Dist: matplotlib ; extra == 'plotting'
Requires-Dist: seaborn ; extra == 'plotting'
Provides-Extra: testing
Requires-Dist: pytest ; extra == 'testing'
